odoo/addons/connector_acp_ftp/README.rst
odoo/addons/connector_acp_ftp/__init__.py
odoo/addons/connector_acp_ftp/__manifest__.py
odoo/addons/connector_acp_ftp/i18n/connector_acp_ftp.pot
odoo/addons/connector_acp_ftp/models/__init__.py
odoo/addons/connector_acp_ftp/models/backend_acp.py
odoo/addons/connector_acp_ftp/readme/CONTRIBUTORS.rst
odoo/addons/connector_acp_ftp/readme/DESCRIPTION.rst
odoo/addons/connector_acp_ftp/readme/USAGE.rst
odoo/addons/connector_acp_ftp/static/description/icon.png
odoo/addons/connector_acp_ftp/static/description/index.html
odoo12_addon_connector_acp_ftp-12.0.1.0.1.dist-info/METADATA
odoo12_addon_connector_acp_ftp-12.0.1.0.1.dist-info/WHEEL
odoo12_addon_connector_acp_ftp-12.0.1.0.1.dist-info/top_level.txt
odoo12_addon_connector_acp_ftp-12.0.1.0.1.dist-info/RECORD
